pyxform/__init__.py
pyxform/aliases.py
pyxform/builder.py
pyxform/constants.py
pyxform/errors.py
pyxform/external_instance.py
pyxform/file_utils.py
pyxform/instance.py
pyxform/json_form_schema.json
pyxform/question.py
pyxform/question_type_dictionary.py
pyxform/section.py
pyxform/survey.py
pyxform/survey_element.py
pyxform/translator.py
pyxform/utils.py
pyxform/xform2json.py
pyxform/xform_instance_parser.py
pyxform/xls2json.py
pyxform/xls2json_backends.py
pyxform/xls2xform.py
pyxform/elements/__init__.py
pyxform/elements/action.py
pyxform/elements/element.py
pyxform/entities/__init__.py
pyxform/entities/entities_parsing.py
pyxform/entities/entity_declaration.py
pyxform/parsing/__init__.py
pyxform/parsing/expression.py
pyxform/parsing/instance_expression.py
pyxform/parsing/sheet_headers.py
pyxform/survey_elements/__init__.py
pyxform/survey_elements/attribute.py
pyxform/survey_elements/label.py
pyxform/translators/nigeria.json
pyxform/util/__init__.py
pyxform/util/enum.py
pyxform/validators/__init__.py
pyxform/validators/error_cleaner.py
pyxform/validators/updater.py
pyxform/validators/util.py
pyxform/validators/xlsform_spec_test.xml
pyxform/validators/enketo_validate/__init__.py
pyxform/validators/odk_validate/.last_check
pyxform/validators/odk_validate/README.rst
pyxform/validators/odk_validate/__init__.py
pyxform/validators/odk_validate/bin/ODK_Validate.jar
pyxform/validators/odk_validate/bin/installed.json
pyxform/validators/pyxform/__init__.py
pyxform/validators/pyxform/android_package_name.py
pyxform/validators/pyxform/choices.py
pyxform/validators/pyxform/parameters_generic.py
pyxform/validators/pyxform/pyxform_reference.py
pyxform/validators/pyxform/question_types.py
pyxform/validators/pyxform/select_from_file.py
pyxform/validators/pyxform/sheet_misspellings.py
pyxform/validators/pyxform/translations_checks.py
pyxform/validators/pyxform/unique_names.py
pyxform/validators/pyxform/iana_subtags/__init__.py
pyxform-4.2.0.dist-info/entry_points.txt
pyxform-4.2.0.dist-info/licenses/LICENSE
pyxform-4.2.0.dist-info/WHEEL
pyxform-4.2.0.dist-info/METADATA
pyxform-4.2.0.dist-info/RECORD
