Metadata-Version: 2.4
Name: pyxform
Version: 4.2.0
Summary: A Python package to create XForms for ODK Collect.
Author-email: "github.com/xlsform" <support@getodk.org>
Requires-Python: >=3.10
License-File: LICENSE
Requires-Dist: xlrd==2.0.1
Requires-Dist: openpyxl==3.1.5
Requires-Dist: defusedxml==0.7.1
Requires-Dist: lark==1.3.1
Requires-Dist: formencode==2.1.1 ; extra == "dev"
Requires-Dist: lxml==6.0.0 ; extra == "dev"
Requires-Dist: psutil==7.0.0 ; extra == "dev"
Requires-Dist: ruff==0.12.4 ; extra == "dev"
Project-URL: Homepage, https://pypi.python.org/pypi/pyxform/
Project-URL: Repository, https://github.com/XLSForm/pyxform/
Provides-Extra: dev
